renderit/__init__.py
renderit/custom_exception.py
renderit/logger.py
renderit/site.py
renderit/youtube.py
renderit-0.0.4.dist-info/LICENSE
renderit-0.0.4.dist-info/METADATA
renderit-0.0.4.dist-info/WHEEL
renderit-0.0.4.dist-info/top_level.txt
renderit-0.0.4.dist-info/RECORD
